mockery/__init__.py
mockery/mockery.py
mockery_translator-0.0.2.dist-info/METADATA
mockery_translator-0.0.2.dist-info/WHEEL
mockery_translator-0.0.2.dist-info/entry_points.txt
mockery_translator-0.0.2.dist-info/top_level.txt
mockery_translator-0.0.2.dist-info/RECORD
