Metadata-Version: 2.1
Name: mockery-translator
Version: 0.0.2
Summary: Translates boring text into mockery
Author: Titus Federwisch
License: MIT
Project-URL: Source, https://github.com/IronRocket/mockery
Keywords: cli,convert,standalone,mockery
Classifier: Development Status :: 6 - Mature
Classifier: Intended Audience :: Developers
Classifier: License :: OSI Approved :: MIT License
Classifier: Natural Language :: English
Classifier: Operating System :: OS Independent
Classifier: Programming Language :: Python
Classifier: Topic :: Software Development :: Libraries
